prophetess/__init__.py
prophetess/__main__.py
prophetess/app.py
prophetess/config.py
prophetess/exceptions.py
prophetess/metrics.py
prophetess/pipeline.py
prophetess/plugin.py
prophetess/utils.py
prophetess/web.py
tests/__init__.py
tests/fixtures.py
tests/test_app.py
tests/test_metrics.py
tests/test_pipeline.py
tests/test_plugin.py
prophetess-0.2.1.dist-info/METADATA
prophetess-0.2.1.dist-info/WHEEL
prophetess-0.2.1.dist-info/top_level.txt
prophetess-0.2.1.dist-info/RECORD
