Metadata-Version: 2.1
Name: prophetess
Version: 0.2.1
Summary: YAML driven ETL
Home-page: https://github.com/vapor-ware/prophetess
Author: Marco Ceppi
Author-email: marco@vapor.io
License: UNKNOWN
Platform: UNKNOWN
Requires-Python: >=3.6
Requires-Dist: aiohttp[speedups]
Requires-Dist: PyYAML
Requires-Dist: prometheus-client
